README.md
setup.py
gym_pycolab/__init__.py
gym_pycolab/pycolab_env.py
gym_pycolab/pycolab_env_test.py
gym_pycolab/pycolab_games.py
gym_pycolab.egg-info/PKG-INFO
gym_pycolab.egg-info/SOURCES.txt
gym_pycolab.egg-info/dependency_links.txt
gym_pycolab.egg-info/requires.txt
gym_pycolab.egg-info/top_level.txt